djangoldp_blog/__init__.py
djangoldp_blog/admin.py
djangoldp_blog/apps.py
djangoldp_blog/djangoldp_settings.py
djangoldp_blog/djangoldp_urls.py
djangoldp_blog/filters.py
djangoldp_blog/models.py
djangoldp_blog/views.py
djangoldp_blog/management/__init__.py
djangoldp_blog/management/commands/__init__.py
djangoldp_blog/migrations/0001_initial.py
djangoldp_blog/migrations/0002_auto_20200810_1432.py
djangoldp_blog/migrations/0003_auto_20220128_1516.py
djangoldp_blog/migrations/0004_auto_20220128_1554.py
djangoldp_blog/migrations/0005_contactlist_document_documenttype.py
djangoldp_blog/migrations/0006_auto_20220131_1722.py
djangoldp_blog/migrations/0007_auto_20220301_1058.py
djangoldp_blog/migrations/0008_auto_20220303_1310.py
djangoldp_blog/migrations/__init__.py
djangoldp_blog/static/js/tinymce/jquery.tinymce.min.js
djangoldp_blog/static/js/tinymce/textarea.js
djangoldp_blog/static/js/tinymce/tinymce.min.js
djangoldp_blog/static/js/tinymce/icons/default/icons.min.js
djangoldp_blog/static/js/tinymce/plugins/advlist/plugin.min.js
djangoldp_blog/static/js/tinymce/plugins/anchor/plugin.min.js
djangoldp_blog/static/js/tinymce/plugins/autolink/plugin.min.js
djangoldp_blog/static/js/tinymce/plugins/autoresize/plugin.min.js
djangoldp_blog/static/js/tinymce/plugins/autosave/plugin.min.js
djangoldp_blog/static/js/tinymce/plugins/bbcode/plugin.min.js
djangoldp_blog/static/js/tinymce/plugins/charmap/plugin.min.js
djangoldp_blog/static/js/tinymce/plugins/code/plugin.min.js
djangoldp_blog/static/js/tinymce/plugins/codesample/plugin.min.js
djangoldp_blog/static/js/tinymce/plugins/colorpicker/plugin.min.js
djangoldp_blog/static/js/tinymce/plugins/contextmenu/plugin.min.js
djangoldp_blog/static/js/tinymce/plugins/directionality/plugin.min.js
djangoldp_blog/static/js/tinymce/plugins/emoticons/plugin.min.js
djangoldp_blog/static/js/tinymce/plugins/emoticons/js/emojiimages.js
djangoldp_blog/static/js/tinymce/plugins/emoticons/js/emojiimages.min.js
djangoldp_blog-1.0.0.dist-info/METADATA
djangoldp_blog-1.0.0.dist-info/WHEEL
djangoldp_blog-1.0.0.dist-info/top_level.txt
djangoldp_blog-1.0.0.dist-info/RECORD
