Metadata-Version: 2.1
Name: djangoldp-blog
Version: 1.0.0
Summary: djangoldp blog package
Home-page: http://git.startinblox.com/djangoldp-packages/djangoldp-blog
Author: Startin'blox
Author-email: nicolas@happy-dev.fr
License: MIT
Platform: UNKNOWN
Requires-Dist: djangoldp (>=2.1)
Requires-Dist: djangoldp-account (>=2.1)
Requires-Dist: Pillow (>=8.0)
Provides-Extra: dev
Requires-Dist: factory-boy (>=2.11.0) ; extra == 'dev'
Requires-Dist: Pillow (>=8.0) ; extra == 'dev'
